createaceproject/ProjectGenerator.py
createaceproject/__init__.py
createaceproject/main.py
createaceproject/templates/classic/doc/images/ansys.gif
createaceproject/templates/classic/docker/README.md
createaceproject/templates/classic/examples/README.md
createaceproject/templates/classic/src/main.py
createaceproject/templates/classic/tests/test_main.py
createaceproject/templates/shared/CHANGELOG.md
createaceproject/templates/shared/CODE_OF_CONDUCT.md
createaceproject/templates/shared/CONTRIBUTING.md
createaceproject/templates/shared/CONTRIBUTING.md.bak
createaceproject/templates/shared/LICENSE
createaceproject/templates/shared/LICENSE.bak
createaceproject/templates/shared/README.md
createaceproject/templates/shared/flake8
createaceproject/templates/shared/gitattributes
createaceproject/templates/shared/gitignore
createaceproject/templates/shared/gitignore.bak
createaceproject/templates/shared/pytest.ini
createaceproject/templates/shared/requirements.txt
createaceproject/templates/shared/requirements_test.txt
ansys_ace_project_gen-0.0.11.dist-info/LICENSE
ansys_ace_project_gen-0.0.11.dist-info/METADATA
ansys_ace_project_gen-0.0.11.dist-info/WHEEL
ansys_ace_project_gen-0.0.11.dist-info/entry_points.txt
ansys_ace_project_gen-0.0.11.dist-info/top_level.txt
ansys_ace_project_gen-0.0.11.dist-info/RECORD
