Metadata-Version: 2.1
Name: ansys-ace-project-gen
Version: 0.0.11
Summary: Ansys ACE Project Generator
Home-page: UNKNOWN
Author: Babacar FALL
Author-email: babacar.fall@ansys.com
License: GNU-GPL
Keywords: python,ansys,ace
Platform: UNKNOWN
Classifier: Development Status :: 1 - Planning
Classifier: Intended Audience :: Developers
Classifier: Operating System :: OS Independent
Classifier: Programming Language :: Python :: 3
License-File: LICENSE
Requires-Dist: easygui
Requires-Dist: coloredlogs
Requires-Dist: emoji
